MANIFEST.in
ez_setup.py
setup.py
dsb/__init__.py
dsb/overloading.py
dsb.egg-info/PKG-INFO
dsb.egg-info/SOURCES.txt
dsb.egg-info/dependency_links.txt
dsb.egg-info/requires.txt
dsb.egg-info/top_level.txt
dsb.egg-info/zip-safe
dsb/accounts/__init__.py
dsb/accounts/middleware.py
dsb/accounts/urls.py
dsb/accounts/views.py
dsb/accounts/templates/registration/autologin.html
dsb/accounts/templates/registration/base.html
dsb/accounts/templates/registration/logged_out.html
dsb/accounts/templates/registration/login.html
dsb/data/__init__.py
dsb/data/json.py
dsb/data/markup.py
dsb/data/models.py
dsb/data/utils.py
dsb/data/views.py
dsb/data/templatetags/__init__.py
dsb/data/templatetags/humanlist.py
dsb/links/__init__.py
dsb/links/decorators.py
dsb/links/templatetags/__init__.py
dsb/links/templatetags/links.py
dsb/services/__init__.py
dsb/services/urls.py
dsb/services/views.py
dsb/services/templates/services/tags/analytics.html
dsb/services/templatetags/__init__.py
dsb/services/templatetags/analytics.py
dsb/timezones/__init__.py
dsb/timezones/middleware.py
dsb/timezones/models.py
dsb/timezones/utils.py
dsb/timezones/templatetags/__init__.py
dsb/timezones/templatetags/tzinfo.py